chemanim/__init__.py
chemanim/bio.py
chemanim/chem_object.py
chemanim/chem_object_3d.py
chemanim/chempy_adapter.py
chemanim/cli.py
chemanim/connect.py
chemanim/core.py
chemanim/data.py
chemanim/rdkit_adapter.py
chemanim/reaction.py
chemanim/viewer_3d.py
chemanim/style/__init__.py
chemanim/style/animations.py
chemanim/style/colors.py
chemanim/style/effects.py
chemanim/style/presets.py
chemanim/style/scene.py
chemanim/style/themes.py
chemanim/style/typography.py
chemanim-0.1.6.dist-info/METADATA
chemanim-0.1.6.dist-info/WHEEL
chemanim-0.1.6.dist-info/entry_points.txt
chemanim-0.1.6.dist-info/licenses/LICENSE
chemanim-0.1.6.dist-info/RECORD
