Metadata-Version: 2.4
Name: chemanim
Version: 0.1.6
Summary: A Manim-based library for chemistry and biochemistry animations
Project-URL: Homepage, https://github.com/Wachirawut2023/Chemanim
Project-URL: Repository, https://github.com/Wachirawut2023/Chemanim
Project-URL: Issues, https://github.com/Wachirawut2023/Chemanim/issues
Author-email: Wachirawut Raksawat <wachirawut2002@gmail.com>
License: MIT
License-File: LICENSE
Keywords: animation,biochemistry,chemistry,manim,molecules,protein,visualization
Classifier: Development Status :: 3 - Alpha
Classifier: Intended Audience :: Education
Classifier: Intended Audience :: Science/Research
Classifier: License :: OSI Approved :: MIT License
Classifier: Programming Language :: Python :: 3
Classifier: Programming Language :: Python :: 3.9
Classifier: Programming Language :: Python :: 3.10
Classifier: Programming Language :: Python :: 3.11
Classifier: Programming Language :: Python :: 3.12
Classifier: Topic :: Scientific/Engineering :: Chemistry
Classifier: Topic :: Scientific/Engineering :: Visualization
Requires-Python: >=3.9
Requires-Dist: biopython
Requires-Dist: networkx
Requires-Dist: numpy
Requires-Dist: pubchempy
Requires-Dist: requests
Provides-Extra: all
Requires-Dist: biotite; extra == 'all'
Requires-Dist: chemformula; extra == 'all'
Requires-Dist: chempy; extra == 'all'
Requires-Dist: manimgl; extra == 'all'
Requires-Dist: py3dmol; extra == 'all'
Requires-Dist: rdkit; extra == 'all'
Provides-Extra: bio
Requires-Dist: biotite; extra == 'bio'
Provides-Extra: chem
Requires-Dist: chemformula; extra == 'chem'
Requires-Dist: chempy; extra == 'chem'
Requires-Dist: rdkit; extra == 'chem'
Provides-Extra: viewer
Requires-Dist: py3dmol; extra == 'viewer'
Provides-Extra: vis
Requires-Dist: manimgl; extra == 'vis'
